{
  "episodeUrl": "https://www.bbc.co.uk/learningenglish/english/features/6-minute-english/ep-190516",
  "title": "Being slim: Is it in our genes?",
  "description": "Studies have shown that about 40% of the variation in a person's weight is influenced by genes.",
  "thumbnailUrl": "https://ichef.bbc.co.uk/images/ic/640x360/p075jswf.jpg",
  "audioUrl": "http://downloads.bbc.co.uk/learningenglish/features/6min/190516_6min_english_slimness_download.mp3",
  "pdfUrl": "http://downloads.bbc.co.uk/learningenglish/features/6min/190516_6min_english_slimness.pdf",
  "vocabItems": [
    {
      "word": "paunch",
      "definition": "fat stomach that mostly men have"
    }
  ],
  "quiz": null
}
