{
  "episodeUrl": "https://www.bbc.co.uk/learningenglish/english/features/6-minute-english/ep-200402",
  "title": "Touring bands and climate change",
  "description": "Music with a smaller carbon footprint",
  "thumbnailUrl": "https://ichef.bbc.co.uk/images/ic/640x360/p088c9vx.jpg",
  "audioUrl": "http://downloads.bbc.co.uk/learningenglish/features/6min/200402_6_min_english_touring_and_climate_download.mp3",
  "pdfUrl": "http://downloads.bbc.co.uk/learningenglish/features/6min/200402_6_min_english_touring_and_climate.pdf",
  "vocabItems": [
    {
      "word": "carbon footprint",
      "definition": "the amount of carbon dioxide or CO2 released into the atmosphere as a result of your everyday activities."
    },
    {
      "word": "turn down",
      "definition": "reject or refuse an offer of something"
    },
    {
      "word": "a precarious situation",
      "definition": "a situation where things could become difficult or dangerous"
    },
    {
      "word": "do the right thing",
      "definition": "do what is most fair, ethical or just."
    },
    {
      "word": "gig",
      "definition": "live concert played by a music band"
    },
    {
      "word": "the (national) grid",
      "definition": "the network supplying electrical power across a country"
    }
  ],
  "quiz": null
}