{
  "episodeUrl": "https://www.bbc.co.uk/learningenglish/english/features/6-minute-english/ep-201029",
  "title": "Walkman: the music player revolution",
  "description": "About 40 years ago, portable music players became a craze with the launch of the Sony Walkman.",
  "thumbnailUrl": "https://ichef.bbc.co.uk/images/ic/640x360/p08w8nwq.jpg",
  "audioUrl": "http://downloads.bbc.co.uk/learningenglish/features/6min/201029_6min_english_walkman_download.mp3",
  "pdfUrl": "http://downloads.bbc.co.uk/learningenglish/features/6min/201029_6min_english_walkman.pdf",
  "vocabItems": [
    {
      "word": "headphones",
      "definition": "pair of padded speakers worn over your ears in order to listen to music without other people hearing"
    },
    {
      "word": "take off",
      "definition": "(phrasal verb) suddenly start to be successful and popular"
    },
    {
      "word": "laid (something) on the line",
      "definition": "(idiom) risked losing something important, such as a job or reputation"
    },
    {
      "word": "picked up on (something)",
      "definition": "(phrasal verb) noticed or gave particular attention to something being said or done"
    },
    {
      "word": "niche product",
      "definition": "something marketed for sale to a small, specific group"
    },
    {
      "word": "caught the public imagination  caught the public's imagination",
      "definition": "caught the public imagination or caught the public's imagination(idiom) made the public interested in or excited about something"
    }
  ],
  "quiz": null
}